despii/__init__.py
despii-0.1.0.dist-info/METADATA
despii-0.1.0.dist-info/WHEEL
despii-0.1.0.dist-info/licenses/LICENSE
despii-0.1.0.dist-info/RECORD
